Metadata-Version: 1.1
Name: diffimg
Version: 0.2.1
Summary: Get the % difference in images + generate a diff image
Home-page: https://github.com/nicolashahn/python-image-diff
Author: Nicolas Hahn
Author-email: nicolas@stonespring.org
License: UNKNOWN
Download-URL: https://github.com/nicolashahn/python-image-diff/archive/v0.2.1.tar.gz
Keywords: diff,difference,image
Platform: UNKNOWN
